publishprs/__init__.py
publishprs/core.py
publishprs-1.0.0.dist-info/LICENSE
publishprs-1.0.0.dist-info/WHEEL
publishprs-1.0.0.dist-info/METADATA
publishprs-1.0.0.dist-info/RECORD
