Metadata-Version: 2.3
Name: publishprs
Version: 1.0.0
Summary: Publish private PRs.
Author-email: Lamin Labs <open-source@lamin.ai>
Requires-Python: >=3.10,<3.14
Requires-Dist: lamindb
Requires-Dist: requests
Requires-Dist: dotenv
Requires-Dist: pre-commit ; extra == "dev"
Requires-Dist: nox ; extra == "dev"
Requires-Dist: pytest>=6.0 ; extra == "dev"
Requires-Dist: pytest-cov ; extra == "dev"
Requires-Dist: nbproject_test ; extra == "dev"
Project-URL: Home, https://github.com/laminlabs/publishprs
Provides-Extra: dev
